shapaclass/model.py
shapaclass-0.1.2.dist-info/LICENSE
shapaclass-0.1.2.dist-info/METADATA
shapaclass-0.1.2.dist-info/WHEEL
shapaclass-0.1.2.dist-info/top_level.txt
shapaclass-0.1.2.dist-info/RECORD
