Metadata-Version: 2.1
Name: shapaclass
Version: 0.1.2
Summary: Classification algorithm based on finding shortest paths
Home-page: https://github.com/rovle/shortest-path-classification
Author: Lovre
Author-email: lovre.pesut@gmail.com
License: MIT
Keywords: machine learning,graphs
Platform: UNKNOWN
Classifier: Programming Language :: Python :: 3
Classifier: License :: OSI Approved :: MIT License
Classifier: Operating System :: OS Independent
Requires-Python: >=3.6
License-File: LICENSE
Requires-Dist: networkx (>=2.5)
Requires-Dist: numpy (>=1.19.2)
